notification_service/__init__.py
notification_service/exceptions.py
notification_service/result.py
notification_service/states.py
notification_service/utils.py
notification_service/baidu/Channel.py
notification_service/baidu/__init__.py
notification_service/baidu/push_core.py
notification_service/jpush/__init__.py
notification_service/jpush/common.py
notification_service/jpush/core.py
notification_service/jpush/push_core.py
notification_service/jpush/device/__init__.py
notification_service/jpush/device/core.py
notification_service/jpush/device/entity.py
notification_service/jpush/push/__init__.py
notification_service/jpush/push/audience.py
notification_service/jpush/push/core.py
notification_service/jpush/push/payload.py
notification_service/push/AWS.py
notification_service/push/__init__.py
notification_service/push/base.py
notification_service/push/jiguang.py
notification_service/push/xinge.py
notification_service/xinge/__init__.py
notification_service/xinge/constant.py
notification_service/xinge/push_core.py
notification_service/xinge/result_status.py
tests/__init__.py
tests/unit/__init__.py
tests/unit/conftest.py
tests/unit/push/__init__.py
tests/unit/push/test_AWS.py
tests/unit/push/test_jiguang.py
tests/unit/push/test_xinge.py
tests/unit/xinge/__init__.py
tests/unit/xinge/test_push_core.py
notification_common_service-0.9.0.dist-info/METADATA
notification_common_service-0.9.0.dist-info/WHEEL
notification_common_service-0.9.0.dist-info/top_level.txt
notification_common_service-0.9.0.dist-info/RECORD
