Metadata-Version: 2.1
Name: notification-common-service
Version: 0.9.0
Summary: Notifcation common service package
Home-page: UNKNOWN
Author: UNKNOWN
Author-email: UNKNOWN
License: UNKNOWN
Keywords: django gizwits
Platform: UNKNOWN
Classifier: Environment :: Web Environment
Classifier: Framework :: Django
Classifier: Programming Language :: Python :: 2.7
Classifier: Topic :: Software Development :: Libraries :: Python Modules
Requires-Dist: requests (==2.8.1)
Requires-Dist: xinge-push (==1.1.8.3)
Requires-Dist: boto3 (==1.4.4)
Requires-Dist: jpush (==3.3.5)
